README.md
setup.py
aidedp_cv/__init__.py
aidedp_cv/dataset_augment.py
aidedp_cv/视频抽帧.py
aidedp_cv.egg-info/PKG-INFO
aidedp_cv.egg-info/SOURCES.txt
aidedp_cv.egg-info/dependency_links.txt
aidedp_cv.egg-info/requires.txt
aidedp_cv.egg-info/top_level.txt
aidedp_cv/shili/__init__.py
aidedp_cv/shili/predict.py
aidedp_cv/shili/requirements.txt.py
aidedp_cv/shili/train.py
aidedp_cv/shili/yolo.ipynb.py
aidedp_cv/shili/说明.py
aidedp_cv/tools/__init__.py
aidedp_cv/tools/buildLabelDistribution.py
aidedp_cv/tools/buildVOCdataset.ipynb.py
aidedp_cv/tools/countlabels.ipynb.py
aidedp_cv/tools/countlabels.py
aidedp_cv/tools/drawBoundingBoxes.py
aidedp_cv/tools/draw_bounding_boxes.ipynb.py
aidedp_cv/tools/imageTransform.py
aidedp_cv/tools/img2jpg.ipynb.py
aidedp_cv/tools/img2jpg.py
aidedp_cv/tools/json2txt.ipynb.py
aidedp_cv/tools/json2txt.py
aidedp_cv/tools/pretreatment_like_yolo.ipynb.py
aidedp_cv/tools/pretreatment_like_yolo.py
aidedp_cv/tools/resultAnalysis.ipynb.py
aidedp_cv/tools/showlabeldistribution.ipynb.py
aidedp_cv/tools/showlabeldistribution.py
aidedp_cv/tools/train_test_split.ipynb.py
aidedp_cv/tools/txt2xml.ipynb.py
aidedp_cv/tools/txt2xml.py
aidedp_cv/tools/xml2txt.ipynb.py
aidedp_cv/tools/xml2txt.py
aidedp_cv/tools/ImageEnhance/__init__.py
aidedp_cv/tools/ImageEnhance/imgCut.ipynb.py
aidedp_cv/tools/ImageEnhance/imgElseEnhance.ipynb.py
aidedp_cv/tools/ImageEnhance/imgMirror.ipynb.py
aidedp_cv/tools/ImageEnhance/imgRotate.ipynb.py
aidedp_cv/tools/ImageEnhance/imgShift.ipynb.py
aidedp_cv/yuyi/__init__.py
aidedp_cv/yuyi/labelme2png.py
aidedp_cv/yuyi/png2labelme.py
aidedp_cv/yuyi/predict_seg.py
aidedp_cv/yuyi/requirements.txt.py
aidedp_cv/yuyi/resnet50-0676ba61.pth.py
aidedp_cv/yuyi/semseg_tutorial_v4.ipynb.py
aidedp_cv/yuyi/train_seg.py
aidedp_cv/yuyi/说明.py